{"nodes": [{"id": "d_mediahive_app_agent_skills_favicon_skill_md", "label": "SKILL.md", "file_type": "document", "source_file": "D:\\MediaHive App\\.agent\\skills\\favicon\\SKILL.md", "source_location": "L1"}, {"id": "favicon_skill_when_to_use", "label": "When to Use", "file_type": "document", "source_file": "D:\\MediaHive App\\.agent\\skills\\favicon\\SKILL.md", "source_location": "L16"}, {"id": "favicon_skill_prerequisites", "label": "Prerequisites", "file_type": "document", "source_file": "D:\\MediaHive App\\.agent\\skills\\favicon\\SKILL.md", "source_location": "L21"}, {"id": "favicon_skill_codeblock_1", "label": "code:bash (which magick)", "file_type": "document", "source_file": "D:\\MediaHive App\\.agent\\skills\\favicon\\SKILL.md", "source_location": "L24"}, {"id": "favicon_skill_step_1_validate_source_image", "label": "Step 1: Validate Source Image", "file_type": "document", "source_file": "D:\\MediaHive App\\.agent\\skills\\favicon\\SKILL.md", "source_location": "L32"}, {"id": "favicon_skill_step_2_detect_project_type_and_static_assets_directory", "label": "Step 2: Detect Project Type and Static Assets Directory", "file_type": "document", "source_file": "D:\\MediaHive App\\.agent\\skills\\favicon\\SKILL.md", "source_location": "L40"}, {"id": "favicon_skill_step_3_determine_app_name", "label": "Step 3: Determine App Name", "file_type": "document", "source_file": "D:\\MediaHive App\\.agent\\skills\\favicon\\SKILL.md", "source_location": "L66"}, {"id": "favicon_skill_step_4_ensure_static_assets_directory_exists", "label": "Step 4: Ensure Static Assets Directory Exists", "file_type": "document", "source_file": "D:\\MediaHive App\\.agent\\skills\\favicon\\SKILL.md", "source_location": "L77"}, {"id": "favicon_skill_step_5_generate_favicon_files", "label": "Step 5: Generate Favicon Files", "file_type": "document", "source_file": "D:\\MediaHive App\\.agent\\skills\\favicon\\SKILL.md", "source_location": "L81"}, {"id": "favicon_skill_favicon_ico_multi_resolution_16x16_32x32_48x48", "label": "favicon.ico (multi-resolution: 16x16, 32x32, 48x48)", "file_type": "document", "source_file": "D:\\MediaHive App\\.agent\\skills\\favicon\\SKILL.md", "source_location": "L87"}, {"id": "favicon_skill_codeblock_2", "label": "code:bash (magick -background none \"$1\" \\)", "file_type": "document", "source_file": "D:\\MediaHive App\\.agent\\skills\\favicon\\SKILL.md", "source_location": "L88"}, {"id": "favicon_skill_favicon_96x96_png", "label": "favicon-96x96.png", "file_type": "document", "source_file": "D:\\MediaHive App\\.agent\\skills\\favicon\\SKILL.md", "source_location": "L97"}, {"id": "favicon_skill_codeblock_3", "label": "code:bash (magick -background none \"$1\" -resize 96x96 -alpha on [STATIC)", "file_type": "document", "source_file": "D:\\MediaHive App\\.agent\\skills\\favicon\\SKILL.md", "source_location": "L98"}, {"id": "favicon_skill_apple_touch_icon_png_180x180", "label": "apple-touch-icon.png (180x180)", "file_type": "document", "source_file": "D:\\MediaHive App\\.agent\\skills\\favicon\\SKILL.md", "source_location": "L102"}, {"id": "favicon_skill_codeblock_4", "label": "code:bash (magick -background none \"$1\" -resize 180x180 -alpha on [STAT)", "file_type": "document", "source_file": "D:\\MediaHive App\\.agent\\skills\\favicon\\SKILL.md", "source_location": "L103"}, {"id": "favicon_skill_web_app_manifest_192x192_png", "label": "web-app-manifest-192x192.png", "file_type": "document", "source_file": "D:\\MediaHive App\\.agent\\skills\\favicon\\SKILL.md", "source_location": "L107"}, {"id": "favicon_skill_codeblock_5", "label": "code:bash (magick -background none \"$1\" -resize 192x192 -alpha on [STAT)", "file_type": "document", "source_file": "D:\\MediaHive App\\.agent\\skills\\favicon\\SKILL.md", "source_location": "L108"}, {"id": "favicon_skill_web_app_manifest_512x512_png", "label": "web-app-manifest-512x512.png", "file_type": "document", "source_file": "D:\\MediaHive App\\.agent\\skills\\favicon\\SKILL.md", "source_location": "L112"}, {"id": "favicon_skill_codeblock_6", "label": "code:bash (magick -background none \"$1\" -resize 512x512 -alpha on [STAT)", "file_type": "document", "source_file": "D:\\MediaHive App\\.agent\\skills\\favicon\\SKILL.md", "source_location": "L113"}, {"id": "favicon_skill_favicon_svg_only_if_source_is_svg", "label": "favicon.svg (only if source is SVG)", "file_type": "document", "source_file": "D:\\MediaHive App\\.agent\\skills\\favicon\\SKILL.md", "source_location": "L117"}, {"id": "favicon_skill_codeblock_7", "label": "code:bash (cp \"$1\" [STATIC_DIR]/favicon.svg)", "file_type": "document", "source_file": "D:\\MediaHive App\\.agent\\skills\\favicon\\SKILL.md", "source_location": "L119"}, {"id": "favicon_skill_step_6_create_update_site_webmanifest", "label": "Step 6: Create/Update site.webmanifest", "file_type": "document", "source_file": "D:\\MediaHive App\\.agent\\skills\\favicon\\SKILL.md", "source_location": "L123"}, {"id": "favicon_skill_codeblock_8", "label": "code:json ({)", "file_type": "document", "source_file": "D:\\MediaHive App\\.agent\\skills\\favicon\\SKILL.md", "source_location": "L127"}, {"id": "favicon_skill_step_7_update_html_layout_files", "label": "Step 7: Update HTML/Layout Files", "file_type": "document", "source_file": "D:\\MediaHive App\\.agent\\skills\\favicon\\SKILL.md", "source_location": "L153"}, {"id": "favicon_skill_for_rails_projects", "label": "For Rails Projects", "file_type": "document", "source_file": "D:\\MediaHive App\\.agent\\skills\\favicon\\SKILL.md", "source_location": "L160"}, {"id": "favicon_skill_codeblock_9", "label": "code:html (<link rel=\"icon\" type=\"image/png\" href=\"/favicon-96x96.png\" )", "file_type": "document", "source_file": "D:\\MediaHive App\\.agent\\skills\\favicon\\SKILL.md", "source_location": "L164"}, {"id": "favicon_skill_for_next_js_projects", "label": "For Next.js Projects", "file_type": "document", "source_file": "D:\\MediaHive App\\.agent\\skills\\favicon\\SKILL.md", "source_location": "L178"}, {"id": "favicon_skill_codeblock_10", "label": "code:typescript (export const metadata: Metadata = {)", "file_type": "document", "source_file": "D:\\MediaHive App\\.agent\\skills\\favicon\\SKILL.md", "source_location": "L182"}, {"id": "favicon_skill_for_static_html_projects", "label": "For Static HTML Projects", "file_type": "document", "source_file": "D:\\MediaHive App\\.agent\\skills\\favicon\\SKILL.md", "source_location": "L206"}, {"id": "favicon_skill_if_no_project_detected", "label": "If No Project Detected", "file_type": "document", "source_file": "D:\\MediaHive App\\.agent\\skills\\favicon\\SKILL.md", "source_location": "L210"}, {"id": "favicon_skill_codeblock_11", "label": "code:html (<link rel=\"icon\" type=\"image/png\" href=\"/favicon-96x96.png\" )", "file_type": "document", "source_file": "D:\\MediaHive App\\.agent\\skills\\favicon\\SKILL.md", "source_location": "L214"}, {"id": "favicon_skill_step_8_summary", "label": "Step 8: Summary", "file_type": "document", "source_file": "D:\\MediaHive App\\.agent\\skills\\favicon\\SKILL.md", "source_location": "L223"}, {"id": "favicon_skill_error_handling", "label": "Error Handling", "file_type": "document", "source_file": "D:\\MediaHive App\\.agent\\skills\\favicon\\SKILL.md", "source_location": "L233"}, {"id": "favicon_skill_limitations", "label": "Limitations", "file_type": "document", "source_file": "D:\\MediaHive App\\.agent\\skills\\favicon\\SKILL.md", "source_location": "L240"}], "edges": [{"source": "d_mediahive_app_agent_skills_favicon_skill_md", "target": "favicon_skill_when_to_use", "relation": "contains", "confidence": "EXTRACTED", "source_file": "D:\\MediaHive App\\.agent\\skills\\favicon\\SKILL.md", "source_location": "L16", "weight": 1.0}, {"source": "d_mediahive_app_agent_skills_favicon_skill_md", "target": "favicon_skill_prerequisites", "relation": "contains", "confidence": "EXTRACTED", "source_file": "D:\\MediaHive App\\.agent\\skills\\favicon\\SKILL.md", "source_location": "L21", "weight": 1.0}, {"source": "favicon_skill_prerequisites", "target": "favicon_skill_codeblock_1", "relation": "contains", "confidence": "EXTRACTED", "source_file": "D:\\MediaHive App\\.agent\\skills\\favicon\\SKILL.md", "source_location": "L24", "weight": 1.0}, {"source": "d_mediahive_app_agent_skills_favicon_skill_md", "target": "favicon_skill_step_1_validate_source_image", "relation": "contains", "confidence": "EXTRACTED", "source_file": "D:\\MediaHive App\\.agent\\skills\\favicon\\SKILL.md", "source_location": "L32", "weight": 1.0}, {"source": "d_mediahive_app_agent_skills_favicon_skill_md", "target": "favicon_skill_step_2_detect_project_type_and_static_assets_directory", "relation": "contains", "confidence": "EXTRACTED", "source_file": "D:\\MediaHive App\\.agent\\skills\\favicon\\SKILL.md", "source_location": "L40", "weight": 1.0}, {"source": "d_mediahive_app_agent_skills_favicon_skill_md", "target": "favicon_skill_step_3_determine_app_name", "relation": "contains", "confidence": "EXTRACTED", "source_file": "D:\\MediaHive App\\.agent\\skills\\favicon\\SKILL.md", "source_location": "L66", "weight": 1.0}, {"source": "d_mediahive_app_agent_skills_favicon_skill_md", "target": "favicon_skill_step_4_ensure_static_assets_directory_exists", "relation": "contains", "confidence": "EXTRACTED", "source_file": "D:\\MediaHive App\\.agent\\skills\\favicon\\SKILL.md", "source_location": "L77", "weight": 1.0}, {"source": "d_mediahive_app_agent_skills_favicon_skill_md", "target": "favicon_skill_step_5_generate_favicon_files", "relation": "contains", "confidence": "EXTRACTED", "source_file": "D:\\MediaHive App\\.agent\\skills\\favicon\\SKILL.md", "source_location": "L81", "weight": 1.0}, {"source": "favicon_skill_step_5_generate_favicon_files", "target": "favicon_skill_favicon_ico_multi_resolution_16x16_32x32_48x48", "relation": "contains", "confidence": "EXTRACTED", "source_file": "D:\\MediaHive App\\.agent\\skills\\favicon\\SKILL.md", "source_location": "L87", "weight": 1.0}, {"source": "favicon_skill_favicon_ico_multi_resolution_16x16_32x32_48x48", "target": "favicon_skill_codeblock_2", "relation": "contains", "confidence": "EXTRACTED", "source_file": "D:\\MediaHive App\\.agent\\skills\\favicon\\SKILL.md", "source_location": "L88", "weight": 1.0}, {"source": "favicon_skill_step_5_generate_favicon_files", "target": "favicon_skill_favicon_96x96_png", "relation": "contains", "confidence": "EXTRACTED", "source_file": "D:\\MediaHive App\\.agent\\skills\\favicon\\SKILL.md", "source_location": "L97", "weight": 1.0}, {"source": "favicon_skill_favicon_96x96_png", "target": "favicon_skill_codeblock_3", "relation": "contains", "confidence": "EXTRACTED", "source_file": "D:\\MediaHive App\\.agent\\skills\\favicon\\SKILL.md", "source_location": "L98", "weight": 1.0}, {"source": "favicon_skill_step_5_generate_favicon_files", "target": "favicon_skill_apple_touch_icon_png_180x180", "relation": "contains", "confidence": "EXTRACTED", "source_file": "D:\\MediaHive App\\.agent\\skills\\favicon\\SKILL.md", "source_location": "L102", "weight": 1.0}, {"source": "favicon_skill_apple_touch_icon_png_180x180", "target": "favicon_skill_codeblock_4", "relation": "contains", "confidence": "EXTRACTED", "source_file": "D:\\MediaHive App\\.agent\\skills\\favicon\\SKILL.md", "source_location": "L103", "weight": 1.0}, {"source": "favicon_skill_step_5_generate_favicon_files", "target": "favicon_skill_web_app_manifest_192x192_png", "relation": "contains", "confidence": "EXTRACTED", "source_file": "D:\\MediaHive App\\.agent\\skills\\favicon\\SKILL.md", "source_location": "L107", "weight": 1.0}, {"source": "favicon_skill_web_app_manifest_192x192_png", "target": "favicon_skill_codeblock_5", "relation": "contains", "confidence": "EXTRACTED", "source_file": "D:\\MediaHive App\\.agent\\skills\\favicon\\SKILL.md", "source_location": "L108", "weight": 1.0}, {"source": "favicon_skill_step_5_generate_favicon_files", "target": "favicon_skill_web_app_manifest_512x512_png", "relation": "contains", "confidence": "EXTRACTED", "source_file": "D:\\MediaHive App\\.agent\\skills\\favicon\\SKILL.md", "source_location": "L112", "weight": 1.0}, {"source": "favicon_skill_web_app_manifest_512x512_png", "target": "favicon_skill_codeblock_6", "relation": "contains", "confidence": "EXTRACTED", "source_file": "D:\\MediaHive App\\.agent\\skills\\favicon\\SKILL.md", "source_location": "L113", "weight": 1.0}, {"source": "favicon_skill_step_5_generate_favicon_files", "target": "favicon_skill_favicon_svg_only_if_source_is_svg", "relation": "contains", "confidence": "EXTRACTED", "source_file": "D:\\MediaHive App\\.agent\\skills\\favicon\\SKILL.md", "source_location": "L117", "weight": 1.0}, {"source": "favicon_skill_favicon_svg_only_if_source_is_svg", "target": "favicon_skill_codeblock_7", "relation": "contains", "confidence": "EXTRACTED", "source_file": "D:\\MediaHive App\\.agent\\skills\\favicon\\SKILL.md", "source_location": "L119", "weight": 1.0}, {"source": "d_mediahive_app_agent_skills_favicon_skill_md", "target": "favicon_skill_step_6_create_update_site_webmanifest", "relation": "contains", "confidence": "EXTRACTED", "source_file": "D:\\MediaHive App\\.agent\\skills\\favicon\\SKILL.md", "source_location": "L123", "weight": 1.0}, {"source": "favicon_skill_step_6_create_update_site_webmanifest", "target": "favicon_skill_codeblock_8", "relation": "contains", "confidence": "EXTRACTED", "source_file": "D:\\MediaHive App\\.agent\\skills\\favicon\\SKILL.md", "source_location": "L127", "weight": 1.0}, {"source": "d_mediahive_app_agent_skills_favicon_skill_md", "target": "favicon_skill_step_7_update_html_layout_files", "relation": "contains", "confidence": "EXTRACTED", "source_file": "D:\\MediaHive App\\.agent\\skills\\favicon\\SKILL.md", "source_location": "L153", "weight": 1.0}, {"source": "favicon_skill_step_7_update_html_layout_files", "target": "favicon_skill_for_rails_projects", "relation": "contains", "confidence": "EXTRACTED", "source_file": "D:\\MediaHive App\\.agent\\skills\\favicon\\SKILL.md", "source_location": "L160", "weight": 1.0}, {"source": "favicon_skill_for_rails_projects", "target": "favicon_skill_codeblock_9", "relation": "contains", "confidence": "EXTRACTED", "source_file": "D:\\MediaHive App\\.agent\\skills\\favicon\\SKILL.md", "source_location": "L164", "weight": 1.0}, {"source": "favicon_skill_step_7_update_html_layout_files", "target": "favicon_skill_for_next_js_projects", "relation": "contains", "confidence": "EXTRACTED", "source_file": "D:\\MediaHive App\\.agent\\skills\\favicon\\SKILL.md", "source_location": "L178", "weight": 1.0}, {"source": "favicon_skill_for_next_js_projects", "target": "favicon_skill_codeblock_10", "relation": "contains", "confidence": "EXTRACTED", "source_file": "D:\\MediaHive App\\.agent\\skills\\favicon\\SKILL.md", "source_location": "L182", "weight": 1.0}, {"source": "favicon_skill_step_7_update_html_layout_files", "target": "favicon_skill_for_static_html_projects", "relation": "contains", "confidence": "EXTRACTED", "source_file": "D:\\MediaHive App\\.agent\\skills\\favicon\\SKILL.md", "source_location": "L206", "weight": 1.0}, {"source": "favicon_skill_step_7_update_html_layout_files", "target": "favicon_skill_if_no_project_detected", "relation": "contains", "confidence": "EXTRACTED", "source_file": "D:\\MediaHive App\\.agent\\skills\\favicon\\SKILL.md", "source_location": "L210", "weight": 1.0}, {"source": "favicon_skill_if_no_project_detected", "target": "favicon_skill_codeblock_11", "relation": "contains", "confidence": "EXTRACTED", "source_file": "D:\\MediaHive App\\.agent\\skills\\favicon\\SKILL.md", "source_location": "L214", "weight": 1.0}, {"source": "d_mediahive_app_agent_skills_favicon_skill_md", "target": "favicon_skill_step_8_summary", "relation": "contains", "confidence": "EXTRACTED", "source_file": "D:\\MediaHive App\\.agent\\skills\\favicon\\SKILL.md", "source_location": "L223", "weight": 1.0}, {"source": "d_mediahive_app_agent_skills_favicon_skill_md", "target": "favicon_skill_error_handling", "relation": "contains", "confidence": "EXTRACTED", "source_file": "D:\\MediaHive App\\.agent\\skills\\favicon\\SKILL.md", "source_location": "L233", "weight": 1.0}, {"source": "d_mediahive_app_agent_skills_favicon_skill_md", "target": "favicon_skill_limitations", "relation": "contains", "confidence": "EXTRACTED", "source_file": "D:\\MediaHive App\\.agent\\skills\\favicon\\SKILL.md", "source_location": "L240", "weight": 1.0}], "input_tokens": 0, "output_tokens": 0}