{"nodes": [{"id": "d_mediahive_app_agent_skills_temporal_golang_pro_resources_testing_strategies_md", "label": "testing-strategies.md", "file_type": "document", "source_file": "D:\\MediaHive App\\.agent\\skills\\temporal-golang-pro\\resources\\testing-strategies.md", "source_location": "L1"}, {"id": "resources_testing_strategies_temporal_go_testing_strategies", "label": "Temporal Go Testing Strategies", "file_type": "document", "source_file": "D:\\MediaHive App\\.agent\\skills\\temporal-golang-pro\\resources\\testing-strategies.md", "source_location": "L1"}, {"id": "resources_testing_strategies_the_test_suite_setup", "label": "The Test Suite Setup", "file_type": "document", "source_file": "D:\\MediaHive App\\.agent\\skills\\temporal-golang-pro\\resources\\testing-strategies.md", "source_location": "L5"}, {"id": "resources_testing_strategies_codeblock_1", "label": "code:go (// Requires: \"github.com/stretchr/testify/suite\", \"go.tempor)", "file_type": "document", "source_file": "D:\\MediaHive App\\.agent\\skills\\temporal-golang-pro\\resources\\testing-strategies.md", "source_location": "L9"}, {"id": "resources_testing_strategies_1_unit_testing_workflows", "label": "1. Unit Testing Workflows", "file_type": "document", "source_file": "D:\\MediaHive App\\.agent\\skills\\temporal-golang-pro\\resources\\testing-strategies.md", "source_location": "L26"}, {"id": "resources_testing_strategies_mocking_activities", "label": "Mocking Activities", "file_type": "document", "source_file": "D:\\MediaHive App\\.agent\\skills\\temporal-golang-pro\\resources\\testing-strategies.md", "source_location": "L30"}, {"id": "resources_testing_strategies_codeblock_2", "label": "code:go (func (s *MyTestSuite) Test_SuccessfulWorkflow() {)", "file_type": "document", "source_file": "D:\\MediaHive App\\.agent\\skills\\temporal-golang-pro\\resources\\testing-strategies.md", "source_location": "L34"}, {"id": "resources_testing_strategies_mocking_child_workflows", "label": "Mocking Child Workflows", "file_type": "document", "source_file": "D:\\MediaHive App\\.agent\\skills\\temporal-golang-pro\\resources\\testing-strategies.md", "source_location": "L50"}, {"id": "resources_testing_strategies_codeblock_3", "label": "code:go (s.env.OnChildWorkflow(MyChildWorkflow, mock.Anything, \"args\")", "file_type": "document", "source_file": "D:\\MediaHive App\\.agent\\skills\\temporal-golang-pro\\resources\\testing-strategies.md", "source_location": "L54"}, {"id": "resources_testing_strategies_2_unit_testing_activities", "label": "2. Unit Testing Activities", "file_type": "document", "source_file": "D:\\MediaHive App\\.agent\\skills\\temporal-golang-pro\\resources\\testing-strategies.md", "source_location": "L58"}, {"id": "resources_testing_strategies_codeblock_4", "label": "code:go (// Requires: \"go.temporal.io/sdk/testsuite\", \"github.com/str)", "file_type": "document", "source_file": "D:\\MediaHive App\\.agent\\skills\\temporal-golang-pro\\resources\\testing-strategies.md", "source_location": "L62"}, {"id": "resources_testing_strategies_3_replay_testing_determinism_check", "label": "3. Replay Testing (Determinism Check)", "file_type": "document", "source_file": "D:\\MediaHive App\\.agent\\skills\\temporal-golang-pro\\resources\\testing-strategies.md", "source_location": "L79"}, {"id": "resources_testing_strategies_codeblock_5", "label": "code:go (func Test_ReplayStaticHistory(t *testing.T) {)", "file_type": "document", "source_file": "D:\\MediaHive App\\.agent\\skills\\temporal-golang-pro\\resources\\testing-strategies.md", "source_location": "L83"}, {"id": "resources_testing_strategies_4_testing_signals_and_queries", "label": "4. Testing Signals and Queries", "file_type": "document", "source_file": "D:\\MediaHive App\\.agent\\skills\\temporal-golang-pro\\resources\\testing-strategies.md", "source_location": "L100"}, {"id": "resources_testing_strategies_codeblock_6", "label": "code:go (func (s *MyTestSuite) Test_WorkflowWithSignal() {)", "file_type": "document", "source_file": "D:\\MediaHive App\\.agent\\skills\\temporal-golang-pro\\resources\\testing-strategies.md", "source_location": "L104"}, {"id": "resources_testing_strategies_best_practices_for_testing", "label": "Best Practices for Testing", "file_type": "document", "source_file": "D:\\MediaHive App\\.agent\\skills\\temporal-golang-pro\\resources\\testing-strategies.md", "source_location": "L122"}, {"id": "resources_testing_strategies_example_testing_an_activity_failure_path", "label": "Example: Testing an Activity Failure Path", "file_type": "document", "source_file": "D:\\MediaHive App\\.agent\\skills\\temporal-golang-pro\\resources\\testing-strategies.md", "source_location": "L129"}, {"id": "resources_testing_strategies_codeblock_7", "label": "code:go (func (s *MyTestSuite) Test_WorkflowHandlesActivityError() {)", "file_type": "document", "source_file": "D:\\MediaHive App\\.agent\\skills\\temporal-golang-pro\\resources\\testing-strategies.md", "source_location": "L131"}], "edges": [{"source": "d_mediahive_app_agent_skills_temporal_golang_pro_resources_testing_strategies_md", "target": "resources_testing_strategies_temporal_go_testing_strategies", "relation": "contains", "confidence": "EXTRACTED", "source_file": "D:\\MediaHive App\\.agent\\skills\\temporal-golang-pro\\resources\\testing-strategies.md", "source_location": "L1", "weight": 1.0}, {"source": "resources_testing_strategies_temporal_go_testing_strategies", "target": "resources_testing_strategies_the_test_suite_setup", "relation": "contains", "confidence": "EXTRACTED", "source_file": "D:\\MediaHive App\\.agent\\skills\\temporal-golang-pro\\resources\\testing-strategies.md", "source_location": "L5", "weight": 1.0}, {"source": "resources_testing_strategies_the_test_suite_setup", "target": "resources_testing_strategies_codeblock_1", "relation": "contains", "confidence": "EXTRACTED", "source_file": "D:\\MediaHive App\\.agent\\skills\\temporal-golang-pro\\resources\\testing-strategies.md", "source_location": "L9", "weight": 1.0}, {"source": "resources_testing_strategies_temporal_go_testing_strategies", "target": "resources_testing_strategies_1_unit_testing_workflows", "relation": "contains", "confidence": "EXTRACTED", "source_file": "D:\\MediaHive App\\.agent\\skills\\temporal-golang-pro\\resources\\testing-strategies.md", "source_location": "L26", "weight": 1.0}, {"source": "resources_testing_strategies_1_unit_testing_workflows", "target": "resources_testing_strategies_mocking_activities", "relation": "contains", "confidence": "EXTRACTED", "source_file": "D:\\MediaHive App\\.agent\\skills\\temporal-golang-pro\\resources\\testing-strategies.md", "source_location": "L30", "weight": 1.0}, {"source": "resources_testing_strategies_mocking_activities", "target": "resources_testing_strategies_codeblock_2", "relation": "contains", "confidence": "EXTRACTED", "source_file": "D:\\MediaHive App\\.agent\\skills\\temporal-golang-pro\\resources\\testing-strategies.md", "source_location": "L34", "weight": 1.0}, {"source": "resources_testing_strategies_1_unit_testing_workflows", "target": "resources_testing_strategies_mocking_child_workflows", "relation": "contains", "confidence": "EXTRACTED", "source_file": "D:\\MediaHive App\\.agent\\skills\\temporal-golang-pro\\resources\\testing-strategies.md", "source_location": "L50", "weight": 1.0}, {"source": "resources_testing_strategies_mocking_child_workflows", "target": "resources_testing_strategies_codeblock_3", "relation": "contains", "confidence": "EXTRACTED", "source_file": "D:\\MediaHive App\\.agent\\skills\\temporal-golang-pro\\resources\\testing-strategies.md", "source_location": "L54", "weight": 1.0}, {"source": "resources_testing_strategies_temporal_go_testing_strategies", "target": "resources_testing_strategies_2_unit_testing_activities", "relation": "contains", "confidence": "EXTRACTED", "source_file": "D:\\MediaHive App\\.agent\\skills\\temporal-golang-pro\\resources\\testing-strategies.md", "source_location": "L58", "weight": 1.0}, {"source": "resources_testing_strategies_2_unit_testing_activities", "target": "resources_testing_strategies_codeblock_4", "relation": "contains", "confidence": "EXTRACTED", "source_file": "D:\\MediaHive App\\.agent\\skills\\temporal-golang-pro\\resources\\testing-strategies.md", "source_location": "L62", "weight": 1.0}, {"source": "resources_testing_strategies_temporal_go_testing_strategies", "target": "resources_testing_strategies_3_replay_testing_determinism_check", "relation": "contains", "confidence": "EXTRACTED", "source_file": "D:\\MediaHive App\\.agent\\skills\\temporal-golang-pro\\resources\\testing-strategies.md", "source_location": "L79", "weight": 1.0}, {"source": "resources_testing_strategies_3_replay_testing_determinism_check", "target": "resources_testing_strategies_codeblock_5", "relation": "contains", "confidence": "EXTRACTED", "source_file": "D:\\MediaHive App\\.agent\\skills\\temporal-golang-pro\\resources\\testing-strategies.md", "source_location": "L83", "weight": 1.0}, {"source": "resources_testing_strategies_temporal_go_testing_strategies", "target": "resources_testing_strategies_4_testing_signals_and_queries", "relation": "contains", "confidence": "EXTRACTED", "source_file": "D:\\MediaHive App\\.agent\\skills\\temporal-golang-pro\\resources\\testing-strategies.md", "source_location": "L100", "weight": 1.0}, {"source": "resources_testing_strategies_4_testing_signals_and_queries", "target": "resources_testing_strategies_codeblock_6", "relation": "contains", "confidence": "EXTRACTED", "source_file": "D:\\MediaHive App\\.agent\\skills\\temporal-golang-pro\\resources\\testing-strategies.md", "source_location": "L104", "weight": 1.0}, {"source": "resources_testing_strategies_temporal_go_testing_strategies", "target": "resources_testing_strategies_best_practices_for_testing", "relation": "contains", "confidence": "EXTRACTED", "source_file": "D:\\MediaHive App\\.agent\\skills\\temporal-golang-pro\\resources\\testing-strategies.md", "source_location": "L122", "weight": 1.0}, {"source": "resources_testing_strategies_best_practices_for_testing", "target": "resources_testing_strategies_example_testing_an_activity_failure_path", "relation": "contains", "confidence": "EXTRACTED", "source_file": "D:\\MediaHive App\\.agent\\skills\\temporal-golang-pro\\resources\\testing-strategies.md", "source_location": "L129", "weight": 1.0}, {"source": "resources_testing_strategies_example_testing_an_activity_failure_path", "target": "resources_testing_strategies_codeblock_7", "relation": "contains", "confidence": "EXTRACTED", "source_file": "D:\\MediaHive App\\.agent\\skills\\temporal-golang-pro\\resources\\testing-strategies.md", "source_location": "L131", "weight": 1.0}], "input_tokens": 0, "output_tokens": 0}